adafruit_cap1188/__init__.py
adafruit_cap1188/cap1188.py
adafruit_cap1188/i2c.py
adafruit_cap1188/spi.py
adafruit_circuitpython_cap1188-1.3.17.dist-info/licenses/LICENSE
adafruit_circuitpython_cap1188-1.3.17.dist-info/METADATA
adafruit_circuitpython_cap1188-1.3.17.dist-info/WHEEL
adafruit_circuitpython_cap1188-1.3.17.dist-info/top_level.txt
adafruit_circuitpython_cap1188-1.3.17.dist-info/RECORD
